lvmapi/__init__.py
lvmapi/app.py
lvmapi/auth.py
lvmapi/broker.py
lvmapi/cache.py
lvmapi/config.yaml
lvmapi/tasks.py
lvmapi/types.py
lvmapi/data/critical_error_email_template.html
lvmapi/data/ephemeris.parquet
lvmapi/data/lvm_logo.png
lvmapi/data/night_log_email_template.html
lvmapi/routers/__init__.py
lvmapi/routers/actors.py
lvmapi/routers/alerts.py
lvmapi/routers/enclosure.py
lvmapi/routers/ephemeris.py
lvmapi/routers/kubernetes.py
lvmapi/routers/logs.py
lvmapi/routers/macros.py
lvmapi/routers/notifications.py
lvmapi/routers/overwatcher.py
lvmapi/routers/slack.py
lvmapi/routers/spectrographs.py
lvmapi/routers/system.py
lvmapi/routers/tasks.py
lvmapi/routers/telescopes.py
lvmapi/routers/transparency.py
lvmapi/routers/weather.py
lvmapi/tools/__init__.py
lvmapi/tools/alerts.py
lvmapi/tools/general.py
lvmapi/tools/gort.py
lvmapi/tools/logs.py
lvmapi/tools/notifications.py
lvmapi/tools/rabbitmq.py
lvmapi/tools/spectrograph.py
lvmapi/tools/telescopes.py
lvmapi/tools/transparency.py
lvmapi-0.2.20.dist-info/METADATA
lvmapi-0.2.20.dist-info/WHEEL
lvmapi-0.2.20.dist-info/licenses/LICENSE.md
lvmapi-0.2.20.dist-info/RECORD
